[
  {
    "fornecedor": "NTTData",
    "total": 18900.64,
    "total_horas": 176.0,
    "detalhes": [
      {
        "perfil": "ESIM - CR de Data de Ativação",
        "hora": 176.0,
        "hh": 0.0,
        "qtde_recursos": 0,
        "alocacao_meses": 1,
        "valor_total": 18900.64
      }
    ]
  },
  {
    "fornecedor": NaN,
    "total": 18900.64,
    "total_horas": 0.0,
    "detalhes": [
      {
        "perfil": NaN,
        "hora": 0.0,
        "hh": 0.0,
        "qtde_recursos": 0,
        "alocacao_meses": 0,
        "valor_total": 0.0
      },
      {
        "perfil": NaN,
        "hora": 0.0,
        "hh": 0.0,
        "qtde_recursos": 0,
        "alocacao_meses": 0,
        "valor_total": 0.0
      },
      {
        "perfil": NaN,
        "hora": 0.0,
        "hh": 0.0,
        "qtde_recursos": 0,
        "alocacao_meses": 0,
        "valor_total": 0.0
      },
      {
        "perfil": NaN,
        "hora": 0.0,
        "hh": 0.0,
        "qtde_recursos": 0,
        "alocacao_meses": 0,
        "valor_total": 0.0
      },
      {
        "perfil": NaN,
        "hora": 0.0,
        "hh": 0.0,
        "qtde_recursos": 0,
        "alocacao_meses": 0,
        "valor_total": 18900.64
      }
    ]
  }
]